blendflare/__init__.py
blendflare/client.py
blendflare/exceptions.py
blendflare/models.py
blendflare/py.typed
blendflare/types.py
blendflare-1.0.3.dist-info/licenses/LICENSE
blendflare-1.0.3.dist-info/METADATA
blendflare-1.0.3.dist-info/WHEEL
blendflare-1.0.3.dist-info/top_level.txt
blendflare-1.0.3.dist-info/RECORD
