Metadata-Version: 2.4
Name: blendflare
Version: 1.0.3
Summary: Official Python SDK for Blendflare API - Search and download 3D assets for Blender
Author-email: Blendflare <support@blendflare.com>
License: MIT
Project-URL: Homepage, https://blendflare.com
Project-URL: Documentation, https://docs.blendflare.com
Project-URL: Repository, https://github.com/blendflare/blendflare-python-sdk
Project-URL: Support, https://blendflare.com/support
Keywords: blender,3d,assets,api,blendflare
Classifier: Development Status :: 5 - Production/Stable
Classifier: Intended Audience :: Developers
Classifier: License :: OSI Approved :: MIT License
Classifier: Programming Language :: Python :: 3
Classifier: Programming Language :: Python :: 3.8
Classifier: Programming Language :: Python :: 3.9
Classifier: Programming Language :: Python :: 3.10
Classifier: Programming Language :: Python :: 3.11
Classifier: Programming Language :: Python :: 3.12
Classifier: Topic :: Software Development :: Libraries :: Python Modules
Requires-Python: >=3.8
License-File: LICENSE
Requires-Dist: requests>=2.31.0
Requires-Dist: typing-extensions>=4.5.0; python_version < "3.11"
Provides-Extra: dev
Requires-Dist: pytest>=7.4.0; extra == "dev"
Requires-Dist: pytest-cov>=4.1.0; extra == "dev"
Requires-Dist: black>=23.7.0; extra == "dev"
Requires-Dist: mypy>=1.5.0; extra == "dev"
Requires-Dist: ruff>=0.0.286; extra == "dev"
Dynamic: license-file
